{"nodes":[{"id":5, "word": "La", "lemma": "le", "nature": "det"}, {"id":2, "word": "cuisine", "lemma": "cuisine", "nature": "nc"}, {"id":3, "word": "est", "lemma": "être", "nature": "v"}, {"id":6, "word": "parfaite", "lemma": "parfait", "nature": "adj"}, {"id":8, "word": "pour", "lemma": "pour", "nature": "prep"}, {"id":9, "word": "un", "lemma": "un", "nature": "det"}, {"id":10, "word": "prix", "lemma": "prix", "nature": "nc"}, {"id":11, "word": "raisonnable", "lemma": "raisonnable", "nature": "adj"}, {"id":15, "word": "en revanche", "lemma": "en revanche", "nature": "adv"}, {"id":16, "word": "la", "lemma": "le", "nature": "det"}, {"id":17, "word": "salle", "lemma": "salle", "nature": "nc"}, {"id":18, "word": "de", "lemma": "de", "nature": "prep"}, {"id":19, "word": "bain", "lemma": "bain", "nature": "nc"}, {"id":20, "word": "et", "lemma": "et", "nature": "coo"}, {"id":21, "word": "les", "lemma": "le", "nature": "det"}, {"id":22, "word": "toilettes", "lemma": "toilette", "nature": "nc"}, {"id":23, "word": "sont", "lemma": "être", "nature": "v"}, {"id":31, "word": "peu", "lemma": "peu", "nature": "adv"}, {"id":28, "word": "propres", "lemma": "propre", "nature": "adj"}],
"edges": [{"source":10, "target":11, "label":"N2"}, {"source":10, "target":9, "label":"det"}, {"source":2, "target":5, "label":"det"}, {"source":18, "target":19, "label":"N2"}, {"source":22, "target":21, "label":"det"}, {"source":20, "target":22, "label":"coord3"}, {"source":17, "target":20, "label":"N2"}, {"source":17, "target":18, "label":"N2"}, {"source":17, "target":16, "label":"det"}, {"source":28, "target":31, "label":"adj"}, {"source":45, "target":33, "label":"void"}, {"source":23, "target":17, "label":"subject"}, {"source":23, "target":15, "label":"S"}, {"source":23, "target":28, "label":"comp"}, {"source":8, "target":10, "label":"N2"}, {"source":49, "target":8, "label":"PP"}, {"source":51, "target":23, "label":"coord"}, {"source":51, "target":14, "label":"void"}, {"source":3, "target":45, "label":"S"}, {"source":3, "target":51, "label":"S"}, {"source":3, "target":49, "label":"vmod"}, {"source":3, "target":6, "label":"comp"}, {"source":3, "target":2, "label":"subject"}]}